osensaimos/__init__.py
osensaimos/anglestest.py
osensaimos/minimalmodbusosensa.py
osensaimos/osensaimos.py
osensaimos/osensaplot.py
osensaimos-0.2.4.dist-info/METADATA
osensaimos-0.2.4.dist-info/RECORD
osensaimos-0.2.4.dist-info/WHEEL
osensaimos-0.2.4.dist-info/top_level.txt
