Metadata-Version: 2.1
Name: osensaimos
Version: 0.2.4
Summary: OSENSA IMOS Python library
Home-page: https://github.com/osensa/osensaimos
Author: OSENSA Innovations
Author-email: cng@osensa.com
License: MIT
